enumerate_iam/__init__.py
enumerate_iam/bruteforce_tests.py
enumerate_iam/generate_bruteforce_tests.py
enumerate_iam/main.py
enumerate_iam/utils/__init__.py
enumerate_iam/utils/json_utils.py
enumerate_iam/utils/remove_metadata.py
aws_enumerateiam-1.0.2.dist-info/LICENSE
aws_enumerateiam-1.0.2.dist-info/METADATA
aws_enumerateiam-1.0.2.dist-info/WHEEL
aws_enumerateiam-1.0.2.dist-info/top_level.txt
aws_enumerateiam-1.0.2.dist-info/RECORD
