Metadata-Version: 2.1
Name: aws-enumerateiam
Version: 1.0.2
Summary: Enumerate the permissions associated with AWS credential set
Home-page: https://github.com/andresrianch/enumerate-iam
Author: andresrianch
Author-email: andresrianch@gmail.com
License: MIT LICENSE
Keywords: aws,enumerate,iam
Platform: UNKNOWN
License-File: LICENSE
Requires-Dist: boto3
Requires-Dist: botocore
